{
  "Workflows": [
    {
      "Path": null,
      "SortBy": 0,
      "VariablesSectionElementsOrder": [],
      "ArgumentsSectionElementsOrder": null,
      "ConstantsSectionElementsOrder": null,
      "AddedNamespaces": null
    },
    {
      "Path": "Acme.xaml",
      "SortBy": 0,
      "VariablesSectionElementsOrder": [
        "index&Sequence_2",
        "text&While_1"
      ],
      "ArgumentsSectionElementsOrder": [],
      "ConstantsSectionElementsOrder": null,
      "AddedNamespaces": null
    }
  ]
}